GitLarder-0.9.2.dist-info/DESCRIPTION.rst
GitLarder-0.9.2.dist-info/METADATA
GitLarder-0.9.2.dist-info/metadata.json
GitLarder-0.9.2.dist-info/RECORD
GitLarder-0.9.2.dist-info/top_level.txt
GitLarder-0.9.2.dist-info/WHEEL
git_larder/__init__.py
